[
    {
        "id": 0,
        "title": "Accomplir tempête.",
        "author": "Alexandria-Aurélie Perrin",
        "published_date": "1966-08-04",
        "genre": "Non-Fiction",
        "price": 7.03,
        "copies_sold": 827088,
        "ran": 0
    },
    {
        "id": 1,
        "title": "Joli indiquer beauté prévenir.",
        "author": "Philippe Coulon",
        "published_date": "1995-02-01",
        "genre": "Non-Fiction",
        "price": 13.85,
        "copies_sold": 567372,
        "ran": 7
    },
    {
        "id": 2,
        "title": "Troisième.",
        "author": "Pierre Delorme",
        "published_date": "1786-06-18",
        "genre": "Thriller",
        "price": 76.08,
        "copies_sold": 675947,
        "ran": 4
    },
    {
        "id": 3,
        "title": "Disparaître permettre couleur sortir.",
        "author": "Pierre Guérin",
        "published_date": "1776-05-31",
        "genre": "Non-Fiction",
        "price": 95.6,
        "copies_sold": 689286,
        "ran": 6
    },
    {
        "id": 4,
        "title": "Briser.",
        "author": "Zoé-Corinne Sanchez",
        "published_date": "1914-04-21",
        "genre": "Non-Fiction",
        "price": 8.44,
        "copies_sold": 808431,
        "ran": 1
    },
    {
        "id": 5,
        "title": "Plan ignorer gauche.",
        "author": "Emmanuel Maillard",
        "published_date": "1813-08-12",
        "genre": "Thriller",
        "price": 24.99,
        "copies_sold": 874396,
        "ran": 7
    },
    {
        "id": 6,
        "title": "Mauvais.",
        "author": "Virginie Leblanc",
        "published_date": "1920-09-07",
        "genre": "Fantasy",
        "price": 65.05,
        "copies_sold": 820919,
        "ran": 7
    },
    {
        "id": 7,
        "title": "Haut rentrer rond écrire.",
        "author": "Éric Delattre",
        "published_date": "1883-12-26",
        "genre": "Fiction",
        "price": 72.13,
        "copies_sold": 869711,
        "ran": 7
    },
    {
        "id": 8,
        "title": "Passer étendue premier.",
        "author": "Stéphane Royer",
        "published_date": "2017-12-14",
        "genre": "Thriller",
        "price": 97.41,
        "copies_sold": 832110,
        "ran": 7
    },
    {
        "id": 9,
        "title": "Avec croix sujet revenir.",
        "author": "Philippe Fernandez-Bonnin",
        "published_date": "2024-07-27",
        "genre": "Science",
        "price": 63.08,
        "copies_sold": 613395,
        "ran": 4
    },
    {
        "id": 10,
        "title": "Droit.",
        "author": "Louis Leclercq",
        "published_date": "1951-03-09",
        "genre": "Fantasy",
        "price": 69.3,
        "copies_sold": 858292,
        "ran": 5
    },
    {
        "id": 11,
        "title": "Subir glace.",
        "author": "Emmanuelle-Madeleine Lopez",
        "published_date": "1978-03-08",
        "genre": "Biography",
        "price": 24.63,
        "copies_sold": 950492,
        "ran": 8
    },
    {
        "id": 12,
        "title": "Champ arme colline chasse.",
        "author": "Antoinette Delannoy-Germain",
        "published_date": "1817-09-23",
        "genre": "Romance",
        "price": 91.07,
        "copies_sold": 669285,
        "ran": 1
    },
    {
        "id": 13,
        "title": "Aspect.",
        "author": "Nathalie Gallet",
        "published_date": "1856-01-27",
        "genre": "Thriller",
        "price": 91.48,
        "copies_sold": 981874,
        "ran": 4
    },
    {
        "id": 14,
        "title": "Titre gloire politique séparer secret besoin difficile.",
        "author": "Noémi Moreno",
        "published_date": "1844-02-27",
        "genre": "Fiction",
        "price": 94.48,
        "copies_sold": 287546,
        "ran": 3
    },
    {
        "id": 15,
        "title": "Fort étranger se dehors.",
        "author": "Danielle Gillet",
        "published_date": "1851-12-13",
        "genre": "Fiction",
        "price": 66.5,
        "copies_sold": 312917,
        "ran": 6
    },
    {
        "id": 16,
        "title": "Conseil parent ci nommer père étoile comme.",
        "author": "Suzanne-Thérèse Delmas",
        "published_date": "1782-01-16",
        "genre": "Thriller",
        "price": 97.59,
        "copies_sold": 692801,
        "ran": 1
    },
    {
        "id": 17,
        "title": "Place.",
        "author": "Daniel Pruvost",
        "published_date": "1857-11-30",
        "genre": "Science",
        "price": 42.38,
        "copies_sold": 714636,
        "ran": 9
    },
    {
        "id": 18,
        "title": "Tromper école corde.",
        "author": "Auguste-René Lemonnier",
        "published_date": "1925-07-10",
        "genre": "Science",
        "price": 70.42,
        "copies_sold": 958360,
        "ran": 5
    },
    {
        "id": 19,
        "title": "Bas mal ne.",
        "author": "Gérard Boucher",
        "published_date": "1867-12-09",
        "genre": "Thriller",
        "price": 8.5,
        "copies_sold": 39168,
        "ran": 0
    },
    {
        "id": 20,
        "title": "Haut.",
        "author": "Marthe du Buisson",
        "published_date": "2001-11-07",
        "genre": "Thriller",
        "price": 44.33,
        "copies_sold": 731990,
        "ran": 7
    },
    {
        "id": 21,
        "title": "Étouffer banc tempête agent.",
        "author": "Margot-Henriette Goncalves",
        "published_date": "1894-06-19",
        "genre": "Romance",
        "price": 91.17,
        "copies_sold": 920492,
        "ran": 8
    },
    {
        "id": 22,
        "title": "Aussi manier secrétaire portier tenter rapidement.",
        "author": "Marguerite Dumont",
        "published_date": "1952-01-11",
        "genre": "Biography",
        "price": 77.68,
        "copies_sold": 639808,
        "ran": 9
    },
    {
        "id": 23,
        "title": "Faute tout.",
        "author": "Amélie Texier",
        "published_date": "1927-12-17",
        "genre": "Science",
        "price": 34.79,
        "copies_sold": 842027,
        "ran": 3
    },
    {
        "id": 24,
        "title": "Poser fidèle larme.",
        "author": "Alexandre Pons",
        "published_date": "1976-06-19",
        "genre": "Thriller",
        "price": 42.54,
        "copies_sold": 974432,
        "ran": 5
    },
    {
        "id": 25,
        "title": "Plusieurs pendre.",
        "author": "Joseph Maury",
        "published_date": "1867-10-28",
        "genre": "Non-Fiction",
        "price": 14.81,
        "copies_sold": 18673,
        "ran": 3
    },
    {
        "id": 26,
        "title": "Pain public.",
        "author": "Christelle Le Gilles",
        "published_date": "1960-10-10",
        "genre": "Biography",
        "price": 64.46,
        "copies_sold": 626796,
        "ran": 5
    },
    {
        "id": 27,
        "title": "Froid fait drôle.",
        "author": "Juliette Mathieu",
        "published_date": "1911-01-11",
        "genre": "Fiction",
        "price": 32.68,
        "copies_sold": 598829,
        "ran": 9
    },
    {
        "id": 28,
        "title": "Connaissance éclater secret.",
        "author": "Tristan-Emmanuel Pineau",
        "published_date": "2022-11-26",
        "genre": "Non-Fiction",
        "price": 5.6899999999999995,
        "copies_sold": 729462,
        "ran": 6
    },
    {
        "id": 29,
        "title": "Paix.",
        "author": "Emmanuel-Joseph Traore",
        "published_date": "1921-07-24",
        "genre": "Thriller",
        "price": 57.67,
        "copies_sold": 509776,
        "ran": 9
    },
    {
        "id": 30,
        "title": "Sans lourd profondément revenir faux bonheur.",
        "author": "Noémi de la Gautier",
        "published_date": "1971-01-27",
        "genre": "Fantasy",
        "price": 17.69,
        "copies_sold": 584810,
        "ran": 2
    },
    {
        "id": 31,
        "title": "Voler autorité.",
        "author": "Lucie Mendès",
        "published_date": "1905-07-09",
        "genre": "Fantasy",
        "price": 75.24,
        "copies_sold": 634942,
        "ran": 7
    },
    {
        "id": 32,
        "title": "Ensemble herbe maison matière voisin bas cou.",
        "author": "Margaret Giraud du Maillard",
        "published_date": "1948-09-12",
        "genre": "Non-Fiction",
        "price": 38.03,
        "copies_sold": 165837,
        "ran": 5
    },
    {
        "id": 33,
        "title": "Après rideau difficile.",
        "author": "Marianne Le Gall",
        "published_date": "2019-11-21",
        "genre": "Fantasy",
        "price": 96.73,
        "copies_sold": 946375,
        "ran": 2
    },
    {
        "id": 34,
        "title": "Accorder nouveau toi témoin.",
        "author": "Jeanne Meyer",
        "published_date": "1985-03-24",
        "genre": "Thriller",
        "price": 29.78,
        "copies_sold": 474950,
        "ran": 9
    },
    {
        "id": 35,
        "title": "Libre esprit distinguer spectacle.",
        "author": "Josette Torres",
        "published_date": "1918-08-01",
        "genre": "Science",
        "price": 36.36,
        "copies_sold": 165469,
        "ran": 2
    },
    {
        "id": 36,
        "title": "Angoisse muet même.",
        "author": "Emmanuelle Perret",
        "published_date": "2004-06-18",
        "genre": "Fiction",
        "price": 75.51,
        "copies_sold": 817789,
        "ran": 1
    },
    {
        "id": 37,
        "title": "Autorité derrière paysage prévenir.",
        "author": "Monique Valette",
        "published_date": "1970-08-21",
        "genre": "Non-Fiction",
        "price": 93.38,
        "copies_sold": 872833,
        "ran": 8
    },
    {
        "id": 38,
        "title": "Lune révolution pointe.",
        "author": "Alexandre Charrier de la Meunier",
        "published_date": "1811-09-09",
        "genre": "Fantasy",
        "price": 27.67,
        "copies_sold": 143600,
        "ran": 4
    },
    {
        "id": 39,
        "title": "Rassurer.",
        "author": "Christiane Da Costa",
        "published_date": "1991-12-26",
        "genre": "Thriller",
        "price": 60.95,
        "copies_sold": 494929,
        "ran": 4
    },
    {
        "id": 40,
        "title": "Aujourd'Hui haut.",
        "author": "Jeanne Faivre",
        "published_date": "1791-09-03",
        "genre": "Thriller",
        "price": 24.8,
        "copies_sold": 870851,
        "ran": 8
    },
    {
        "id": 41,
        "title": "Violence visite.",
        "author": "Roger de la Lecomte",
        "published_date": "1860-08-16",
        "genre": "Romance",
        "price": 84.52,
        "copies_sold": 712604,
        "ran": 0
    },
    {
        "id": 42,
        "title": "Soumettre passer semblable âgé sou.",
        "author": "Inès Normand",
        "published_date": "1965-10-13",
        "genre": "Fantasy",
        "price": 59.63,
        "copies_sold": 442205,
        "ran": 5
    },
    {
        "id": 43,
        "title": "Lutte rare relation renoncer moins empêcher nombreux ah.",
        "author": "Chantal-Stéphanie Masse",
        "published_date": "1989-01-19",
        "genre": "Non-Fiction",
        "price": 55.53,
        "copies_sold": 219550,
        "ran": 0
    },
    {
        "id": 44,
        "title": "Cabinet gagner signe ombre.",
        "author": "Denise Letellier",
        "published_date": "1964-06-18",
        "genre": "Thriller",
        "price": 13.65,
        "copies_sold": 398385,
        "ran": 0
    },
    {
        "id": 45,
        "title": "Troisième.",
        "author": "Alix Le Grégoire",
        "published_date": "1789-12-15",
        "genre": "Science",
        "price": 98.66,
        "copies_sold": 18543,
        "ran": 0
    },
    {
        "id": 46,
        "title": "Amour rapidement sourd défendre.",
        "author": "Victoire Bruneau de Cousin",
        "published_date": "1835-10-27",
        "genre": "Fantasy",
        "price": 27.33,
        "copies_sold": 169064,
        "ran": 6
    },
    {
        "id": 47,
        "title": "Main accrocher éclat perdu usage.",
        "author": "Emmanuelle Gonzalez de Guibert",
        "published_date": "1851-10-23",
        "genre": "Romance",
        "price": 82.63,
        "copies_sold": 965210,
        "ran": 0
    },
    {
        "id": 48,
        "title": "Habiter et dur.",
        "author": "Augustin Verdier",
        "published_date": "1958-06-27",
        "genre": "Biography",
        "price": 47.67,
        "copies_sold": 742516,
        "ran": 9
    },
    {
        "id": 49,
        "title": "Ouvrir.",
        "author": "Édith du Gautier",
        "published_date": "1913-11-01",
        "genre": "Biography",
        "price": 47.83,
        "copies_sold": 616184,
        "ran": 8
    },
    {
        "id": 50,
        "title": "Permettre bois beau pousser.",
        "author": "Timothée Legrand",
        "published_date": "1935-05-14",
        "genre": "Science",
        "price": 97.78,
        "copies_sold": 505336,
        "ran": 4
    },
    {
        "id": 51,
        "title": "Sens.",
        "author": "Adrienne Benard",
        "published_date": "1784-01-21",
        "genre": "Biography",
        "price": 32.13,
        "copies_sold": 845199,
        "ran": 7
    },
    {
        "id": 52,
        "title": "Conclure mourir disposer sauvage rapidement ruine encore.",
        "author": "Alexandria Dupré Le Allard",
        "published_date": "1860-08-26",
        "genre": "Non-Fiction",
        "price": 16.66,
        "copies_sold": 807985,
        "ran": 3
    },
    {
        "id": 53,
        "title": "Aimer.",
        "author": "Augustin Leroy",
        "published_date": "1985-07-23",
        "genre": "Biography",
        "price": 83.44,
        "copies_sold": 649102,
        "ran": 6
    },
    {
        "id": 54,
        "title": "Foi battre avenir.",
        "author": "Marthe Chevallier",
        "published_date": "1863-09-26",
        "genre": "Fiction",
        "price": 8.16,
        "copies_sold": 140143,
        "ran": 7
    },
    {
        "id": 55,
        "title": "Billet disparaître.",
        "author": "Alfred Maurice",
        "published_date": "1859-11-26",
        "genre": "Biography",
        "price": 68.76,
        "copies_sold": 86209,
        "ran": 8
    },
    {
        "id": 56,
        "title": "Secret geste enfin me.",
        "author": "Henriette Neveu du Picard",
        "published_date": "1931-03-24",
        "genre": "Romance",
        "price": 68.83,
        "copies_sold": 146435,
        "ran": 6
    },
    {
        "id": 57,
        "title": "Prince fin montrer différent existence unique.",
        "author": "Thibault-Honoré Menard",
        "published_date": "1848-10-16",
        "genre": "Non-Fiction",
        "price": 82.8,
        "copies_sold": 609123,
        "ran": 7
    },
    {
        "id": 58,
        "title": "Noir.",
        "author": "Anaïs Lévêque",
        "published_date": "1934-05-07",
        "genre": "Thriller",
        "price": 96.0,
        "copies_sold": 9198,
        "ran": 8
    },
    {
        "id": 59,
        "title": "Simple.",
        "author": "Étienne Ollivier du Gilles",
        "published_date": "1995-09-01",
        "genre": "Romance",
        "price": 41.4,
        "copies_sold": 970216,
        "ran": 8
    },
    {
        "id": 60,
        "title": "Donc traiter pencher asseoir.",
        "author": "Margaret Boucher de la Gomes",
        "published_date": "1798-09-01",
        "genre": "Biography",
        "price": 51.46,
        "copies_sold": 447826,
        "ran": 4
    },
    {
        "id": 61,
        "title": "Plonger deviner toute offrir.",
        "author": "Martine Bourgeois",
        "published_date": "1902-01-29",
        "genre": "Thriller",
        "price": 28.07,
        "copies_sold": 395386,
        "ran": 9
    },
    {
        "id": 62,
        "title": "Terrible science rendre cerveau fer.",
        "author": "Olivie Raynaud",
        "published_date": "2004-05-20",
        "genre": "Non-Fiction",
        "price": 46.71,
        "copies_sold": 463475,
        "ran": 5
    },
    {
        "id": 63,
        "title": "Paraître robe prochain ministre.",
        "author": "Luc Lebreton",
        "published_date": "1840-01-27",
        "genre": "Science",
        "price": 62.11,
        "copies_sold": 172061,
        "ran": 8
    },
    {
        "id": 64,
        "title": "Sonner possible argent passage.",
        "author": "Laurent de la Bouchet",
        "published_date": "2009-06-01",
        "genre": "Biography",
        "price": 14.24,
        "copies_sold": 160117,
        "ran": 4
    },
    {
        "id": 65,
        "title": "Conduire masse.",
        "author": "Anastasie Guillot",
        "published_date": "1918-12-03",
        "genre": "Thriller",
        "price": 66.5,
        "copies_sold": 100647,
        "ran": 2
    },
    {
        "id": 66,
        "title": "Calmer chaud certain.",
        "author": "Michèle Duval",
        "published_date": "1994-05-10",
        "genre": "Fiction",
        "price": 15.99,
        "copies_sold": 216013,
        "ran": 2
    },
    {
        "id": 67,
        "title": "Devenir tapis goutte.",
        "author": "Timothée Alves du Rolland",
        "published_date": "1790-12-03",
        "genre": "Fiction",
        "price": 31.88,
        "copies_sold": 315298,
        "ran": 6
    },
    {
        "id": 68,
        "title": "Vivre maître puis deviner vague.",
        "author": "Éric Prévost",
        "published_date": "1927-02-09",
        "genre": "Fiction",
        "price": 48.99,
        "copies_sold": 538051,
        "ran": 5
    },
    {
        "id": 69,
        "title": "Il ce avoir peuple partie.",
        "author": "Catherine Le Dufour",
        "published_date": "2006-01-12",
        "genre": "Science",
        "price": 66.05,
        "copies_sold": 394888,
        "ran": 0
    },
    {
        "id": 70,
        "title": "Parce Que pour.",
        "author": "Anouk de Paul",
        "published_date": "1868-01-22",
        "genre": "Romance",
        "price": 67.05,
        "copies_sold": 680640,
        "ran": 0
    },
    {
        "id": 71,
        "title": "Sol.",
        "author": "Geneviève Pruvost-Thierry",
        "published_date": "1805-01-24",
        "genre": "Science",
        "price": 69.71,
        "copies_sold": 798901,
        "ran": 3
    },
    {
        "id": 72,
        "title": "Peser partir.",
        "author": "Thibault Klein",
        "published_date": "1858-03-13",
        "genre": "Thriller",
        "price": 48.54,
        "copies_sold": 498250,
        "ran": 0
    },
    {
        "id": 73,
        "title": "Mauvais entretenir soir craindre.",
        "author": "Grégoire de Guibert",
        "published_date": "1999-11-13",
        "genre": "Biography",
        "price": 87.03,
        "copies_sold": 491511,
        "ran": 0
    },
    {
        "id": 74,
        "title": "Puisque yeux neuf.",
        "author": "Théophile Marion",
        "published_date": "1876-10-12",
        "genre": "Non-Fiction",
        "price": 16.57,
        "copies_sold": 928589,
        "ran": 3
    },
    {
        "id": 75,
        "title": "Déchirer bientôt accorder.",
        "author": "Noémi Jacob de Roche",
        "published_date": "1936-11-18",
        "genre": "Romance",
        "price": 17.43,
        "copies_sold": 106665,
        "ran": 8
    },
    {
        "id": 76,
        "title": "Coeur.",
        "author": "Alexandria Renaud",
        "published_date": "1875-10-15",
        "genre": "Fantasy",
        "price": 30.93,
        "copies_sold": 345058,
        "ran": 9
    },
    {
        "id": 77,
        "title": "Attendre genou.",
        "author": "Simone Dupré",
        "published_date": "1831-01-23",
        "genre": "Biography",
        "price": 91.57,
        "copies_sold": 536021,
        "ran": 5
    },
    {
        "id": 78,
        "title": "Peur portier vue du ça lors.",
        "author": "Maryse Bigot",
        "published_date": "1856-02-20",
        "genre": "Fiction",
        "price": 23.23,
        "copies_sold": 828458,
        "ran": 1
    },
    {
        "id": 79,
        "title": "Siège tel sourire.",
        "author": "Camille Delorme",
        "published_date": "1922-03-13",
        "genre": "Science",
        "price": 16.71,
        "copies_sold": 606645,
        "ran": 8
    },
    {
        "id": 80,
        "title": "Humide.",
        "author": "Capucine Gimenez",
        "published_date": "1788-09-07",
        "genre": "Fiction",
        "price": 31.11,
        "copies_sold": 100647,
        "ran": 6
    },
    {
        "id": 81,
        "title": "Principe siècle rêver prendre.",
        "author": "Théophile de la Salmon",
        "published_date": "1996-07-09",
        "genre": "Science",
        "price": 51.35,
        "copies_sold": 929643,
        "ran": 8
    },
    {
        "id": 82,
        "title": "Appartenir installer appel allumer ça supérieur condamner.",
        "author": "Pénélope de la Klein",
        "published_date": "1898-02-20",
        "genre": "Fiction",
        "price": 69.09,
        "copies_sold": 862663,
        "ran": 3
    },
    {
        "id": 83,
        "title": "Billet nom juger.",
        "author": "Nathalie Jacquot",
        "published_date": "2005-06-22",
        "genre": "Science",
        "price": 42.09,
        "copies_sold": 439933,
        "ran": 3
    },
    {
        "id": 84,
        "title": "Puisque.",
        "author": "Manon de la Mahe",
        "published_date": "1839-08-11",
        "genre": "Romance",
        "price": 72.41,
        "copies_sold": 253881,
        "ran": 3
    },
    {
        "id": 85,
        "title": "Mauvais bord sans banc rencontrer.",
        "author": "Antoine du Bailly",
        "published_date": "1836-04-21",
        "genre": "Thriller",
        "price": 28.92,
        "copies_sold": 199031,
        "ran": 3
    },
    {
        "id": 86,
        "title": "Commun.",
        "author": "Henri Baron",
        "published_date": "1905-08-13",
        "genre": "Non-Fiction",
        "price": 12.72,
        "copies_sold": 652921,
        "ran": 4
    },
    {
        "id": 87,
        "title": "Prouver parmi comme chat.",
        "author": "Virginie Lucas",
        "published_date": "1932-07-07",
        "genre": "Non-Fiction",
        "price": 22.63,
        "copies_sold": 844385,
        "ran": 7
    },
    {
        "id": 88,
        "title": "Compagnon crainte différent.",
        "author": "Valérie Diaz",
        "published_date": "1993-08-26",
        "genre": "Non-Fiction",
        "price": 83.68,
        "copies_sold": 410186,
        "ran": 1
    },
    {
        "id": 89,
        "title": "Peser flamme contre.",
        "author": "Joséphine Gaillard",
        "published_date": "1809-01-04",
        "genre": "Non-Fiction",
        "price": 60.32,
        "copies_sold": 901170,
        "ran": 8
    },
    {
        "id": 90,
        "title": "Habitude fond fois.",
        "author": "Hugues Le Gall",
        "published_date": "1955-06-25",
        "genre": "Romance",
        "price": 11.05,
        "copies_sold": 98562,
        "ran": 0
    },
    {
        "id": 91,
        "title": "Extraordinaire.",
        "author": "Gilbert Lemoine-Pereira",
        "published_date": "1949-02-01",
        "genre": "Fiction",
        "price": 19.96,
        "copies_sold": 791227,
        "ran": 5
    },
    {
        "id": 92,
        "title": "Faire changement homme.",
        "author": "Marcel Besnard",
        "published_date": "1802-08-24",
        "genre": "Non-Fiction",
        "price": 62.94,
        "copies_sold": 542548,
        "ran": 2
    },
    {
        "id": 93,
        "title": "Mode ailleurs trace.",
        "author": "Inès de Rodriguez",
        "published_date": "1861-06-06",
        "genre": "Non-Fiction",
        "price": 5.3,
        "copies_sold": 47693,
        "ran": 2
    },
    {
        "id": 94,
        "title": "Réponse avoir servir pur savoir.",
        "author": "Anouk Boucher",
        "published_date": "1843-08-12",
        "genre": "Romance",
        "price": 50.49,
        "copies_sold": 845278,
        "ran": 2
    },
    {
        "id": 95,
        "title": "Éteindre.",
        "author": "René Da Silva-Bourdon",
        "published_date": "1813-01-11",
        "genre": "Fantasy",
        "price": 87.59,
        "copies_sold": 547842,
        "ran": 5
    },
    {
        "id": 96,
        "title": "Seigneur satisfaire nombre haine élever.",
        "author": "Dorothée Faure",
        "published_date": "1914-11-17",
        "genre": "Science",
        "price": 81.57,
        "copies_sold": 97509,
        "ran": 4
    },
    {
        "id": 97,
        "title": "Honte officier réduire désigner car.",
        "author": "Frédérique du Sauvage",
        "published_date": "1925-02-06",
        "genre": "Romance",
        "price": 40.33,
        "copies_sold": 993553,
        "ran": 1
    },
    {
        "id": 98,
        "title": "Faute blond sueur.",
        "author": "Madeleine Gallet",
        "published_date": "1798-06-15",
        "genre": "Romance",
        "price": 19.78,
        "copies_sold": 301349,
        "ran": 9
    },
    {
        "id": 99,
        "title": "Existence commencement ruine contenir nous mille feuille éviter.",
        "author": "Alice Benard",
        "published_date": "1986-06-29",
        "genre": "Romance",
        "price": 40.81,
        "copies_sold": 741008,
        "ran": 7
    }
]